neuralml/rede.py
neuralml-0.2.6.dist-info/METADATA
neuralml-0.2.6.dist-info/WHEEL
neuralml-0.2.6.dist-info/top_level.txt
neuralml-0.2.6.dist-info/RECORD
