Metadata-Version: 2.1
Name: neuralml
Version: 0.2.6
Summary: Biblioteca para criar rede neurais simples
Home-page: https://github.com/marcyhel/Neural-ML
Author: Marcyhel da Silva Menezes
Author-email: h.marcyhel2012@gmail.com
License: MIT License
Keywords: Pacote Rede Neural IA AI
Requires-Dist: numpy
